MANIFEST.in
README
setup.py
btcnet_info/__init__.py
btcnet_info/api.py
btcnet_info/baseobject.py
btcnet_info/coins.py
btcnet_info/difficulty_sites.py
btcnet_info/exchanges.py
btcnet_info/node.py
btcnet_info/node_handle.py
btcnet_info/objects.py
btcnet_info/pools.py
btcnet_info/test.py
btcnet_info/transfer_coins.py
btcnet_info/version.py
btcnet_info.egg-info/PKG-INFO
btcnet_info.egg-info/SOURCES.txt
btcnet_info.egg-info/dependency_links.txt
btcnet_info.egg-info/requires.txt
btcnet_info.egg-info/top_level.txt
btcnet_info/coins/btc
btcnet_info/coins/geg
btcnet_info/coins/i0c
btcnet_info/coins/ixc
btcnet_info/coins/nmc
btcnet_info/coins/scc
btcnet_info/difficulty_sites/allchains
btcnet_info/difficulty_sites/blockexplorer
btcnet_info/difficulty_sites/dotbit
btcnet_info/difficulty_sites/ixcoino
btcnet_info/difficulty_sites/sccoino
btcnet_info/exchanges/bitparking
btcnet_info/exchanges/btc-e
btcnet_info/pools/abc
btcnet_info/pools/asspenny
btcnet_info/pools/bcpool
btcnet_info/pools/bitcash
btcnet_info/pools/bitclockers
btcnet_info/pools/bithasher
btcnet_info/pools/bitminter
btcnet_info/pools/bitparking
btcnet_info/pools/bitpenny
btcnet_info/pools/btcg
btcnet_info/pools/btcmine
btcnet_info/pools/btcpool24
btcnet_info/pools/btcwarp
btcnet_info/pools/coinotron
btcnet_info/pools/deepbit
btcnet_info/pools/eclipsemc
btcnet_info/pools/eligius
btcnet_info/pools/fiftybtc
btcnet_info/pools/guildminers
btcnet_info/pools/hashpower
btcnet_info/pools/itzod
btcnet_info/pools/maxbtc
btcnet_info/pools/mkalinin
btcnet_info/pools/mtred
btcnet_info/pools/nmcbit
btcnet_info/pools/nmcbitbtc
btcnet_info/pools/oldpolmine
btcnet_info/pools/ozco
btcnet_info/pools/project2
btcnet_info/pools/simplecoin
btcnet_info/pools/slush
btcnet_info/pools/triple