Metadata-Version: 1.1
Name: btcnet-info
Version: 0.1.2.36
Summary: BitCoin Network Information Library
Home-page: github.com/c00w/btcnet_info
Author: Colin Rice
Author-email: dah4k0r@gmail.com
License: MIT Expat License
Platform: UNKNOWN
Classifier: Development Status :: 4 - Beta
Classifier: Intended Audience :: Developers
Classifier: Topic :: System :: Networking
Classifier: License :: OSI Approved :: MIT License
